apis_import_project/.gitignore
apis_import_project/__init__.py
apis_import_project/admin.py
apis_import_project/apps.py
apis_import_project/forms.py
apis_import_project/logger.py
apis_import_project/migrations/0001_initial.py
apis_import_project/migrations/__init__.py
apis_import_project/models.py
apis_import_project/pdf_logger.py
apis_import_project/serializers.py
apis_import_project/static/apis_import_project/css/autocomplete.css
apis_import_project/static/apis_import_project/css/main.css
apis_import_project/static/apis_import_project/js/autocomplete.js
apis_import_project/static/apis_import_project/js/autocomplete.js.map
apis_import_project/static/apis_import_project/js/pdf_tool.js
apis_import_project/tables.py
apis_import_project/templates/element_templates/autoDate_button_generic_ajax_form.html
apis_import_project/templates/element_templates/custom_ajax_form_generic.html
apis_import_project/templates/element_templates/element_datasource_update.html
apis_import_project/templates/element_templates/element_datasources_select_template.html
apis_import_project/templates/element_templates/element_datasources_upload.html
apis_import_project/templates/element_templates/element_project_create.html
apis_import_project/templates/pages/editor_page.html
apis_import_project/templates/pages/projects_page.html
apis_import_project/templates/section_templates/datasource_browser.html
apis_import_project/templates/section_templates/generic_create_items_section.html
apis_import_project/templates/section_templates/generic_entity_meta_section.html
apis_import_project/templates/section_templates/generic_process_section.html
apis_import_project/templates/section_templates/generic_relations_section.html
apis_import_project/templates/section_templates/progress_created_template.html
apis_import_project/templates/section_templates/progress_deleted_template.html
apis_import_project/templates/section_templates/progress_edited_template.html
apis_import_project/tests.py
apis_import_project-0.4.0.dist-info/WHEEL
apis_import_project-0.4.0.dist-info/METADATA
apis_import_project-0.4.0.dist-info/RECORD
