Metadata-Version: 2.1
Name: apis-import-project
Version: 0.4.0
Summary: Generic Django-App for APIS-instances to support importing new data manually with a streamlined workflow and some automation.
Author: Gregor Pirgie
Author-email: gregor.pirgie@oeaw.ac.at
Classifier: Programming Language :: Python :: 2
Classifier: Programming Language :: Python :: 2.7
Classifier: Programming Language :: Python :: 3
Classifier: Programming Language :: Python :: 3.10
Classifier: Programming Language :: Python :: 3.4
Classifier: Programming Language :: Python :: 3.5
Classifier: Programming Language :: Python :: 3.6
Classifier: Programming Language :: Python :: 3.7
Classifier: Programming Language :: Python :: 3.8
Classifier: Programming Language :: Python :: 3.9
